{"01": {"total": 83, "completed": 81, "moved": 11}, "02": {"total": 84, "completed": 82, "moved": 6}, "03": {"total": 81, "completed": 79, "moved": 4}, "04": {"total": 88, "completed": 83, "repeated": 1, "moved": 8}, "05": {"total": 82, "completed": 79, "repeated": 1, "moved": 11}, "06": {"total": 84, "completed": 72, "repeated": 4, "moved": 9}, "07": {"total": 87, "completed": 75, "moved": 21}, "08": {"total": 90, "completed": 78, "repeated": 1, "moved": 10}, "1B": {"total": 47, "completed": 46, "moved": 7}, "2B": {"total": 56, "completed": 56, "moved": 1}, "3B": {"total": 39}}