{"01": {"total": 86, "completed": 53, "repeated": 12, "moved": 10}, "02": {"total": 58, "completed": 41, "repeated": 9, "moved": 6}, "03": {"total": 71, "completed": 48, "repeated": 8, "moved": 8}, "04": {"total": 72, "completed": 51, "repeated": 2, "moved": 6}, "05": {"total": 99, "completed": 61, "repeated": 10, "moved": 7}, "06": {"total": 60, "completed": 47, "repeated": 4, "moved": 4}, "07": {"total": 68, "completed": 53, "repeated": 3, "moved": 6}, "08": {"total": 56, "completed": 44, "repeated": 3, "moved": 5}}