{"01": {"total": 120, "completed": 94, "repeated": 4, "moved": 12}, "02": {"total": 112, "completed": 78, "repeated": 7, "moved": 5}, "03": {"total": 118, "completed": 91, "repeated": 3, "moved": 4}, "04": {"total": 123, "completed": 96, "repeated": 3, "moved": 9}, "05": {"total": 140, "completed": 88, "repeated": 1, "moved": 10}, "06": {"total": 136, "completed": 119, "moved": 8}, "07": {"total": 183, "completed": 137, "repeated": 15, "moved": 17}, "08": {"total": 167, "completed": 71, "repeated": 3, "moved": 9}, "1B": {"total": 353, "completed": 259, "repeated": 43, "moved": 50}, "2B": {"total": 217, "completed": 92, "repeated": 16, "moved": 15}, "3B": {"total": 146, "repeated": 3, "moved": 1}}