{"2013":{"1":{"total":152},"2":{"total":156},"3":{"total":139},"4":{"total":131}},"2014":{"1":{"total":145},"2":{"total":147},"3":{"total":149},"4":{"total":160},"laptops":0},"2015":{"1":{"total":130},"2":{"total":138},"3":{"total":139},"4":{"total":137},"laptops":1},"2016":{"1":{"total":121},"2":{"total":108},"3":{"total":140},"4":{"total":124},"laptops":2},"2017":{"1":{"total":33},"2":{"total":83},"3":{"total":70},"4":{"total":61}},"paquete":[2014,2016],"leche":[2014,2016],"parents":[2014,2016]}