{"01": {"total": 133, "completed": 95, "repeated": 23, "moved": 3}, "02": {"total": 86, "completed": 79, "repeated": 4, "moved": 2}, "03": {"total": 110, "completed": 86, "repeated": 15, "moved": 2}, "04": {"total": 124, "completed": 103, "repeated": 6, "moved": 4}, "05": {"total": 92, "completed": 75, "repeated": 9, "moved": 2}, "06": {"total": 82, "completed": 63, "repeated": 4, "moved": 1}, "07": {"total": 78, "completed": 67, "repeated": 1, "moved": 1}, "08": {"total": 89, "completed": 76, "repeated": 3, "moved": 1}}