{"01": {"total": 80, "completed": 56, "repeated": 11, "moved": 6}, "02": {"total": 69, "completed": 55, "repeated": 1, "moved": 1}, "03": {"total": 62, "completed": 50, "repeated": 4, "moved": 4}, "04": {"total": 73, "completed": 56, "repeated": 6, "moved": 1}, "05": {"total": 75, "completed": 63, "repeated": 6, "moved": 9}, "06": {"total": 85, "completed": 66, "repeated": 7, "moved": 4}, "07": {"total": 84, "completed": 62, "repeated": 10, "moved": 8}, "08": {"total": 84, "completed": 71, "repeated": 5, "moved": 4}}