{"01": {"total": 119, "completed": 86, "repeated": 18, "moved": 22}, "02": {"total": 97, "completed": 83, "repeated": 5, "moved": 8}, "03": {"total": 80, "completed": 71, "repeated": 3, "moved": 10}, "04": {"total": 104, "completed": 85, "repeated": 3, "moved": 10}, "05": {"total": 93, "completed": 72, "repeated": 7, "moved": 12}, "06": {"total": 109, "completed": 92, "repeated": 5, "moved": 18}, "07": {"total": 157, "completed": 125, "repeated": 10, "moved": 25}, "08": {"total": 145, "completed": 116, "repeated": 6, "moved": 18}, "1B": {"total": 47, "completed": 19, "repeated": 15, "moved": 14}, "2B": {"total": 36, "repeated": 3, "moved": 3}}