{"01": {"total": 42, "completed": 39, "repeated": 2, "moved": 2}, "02": {"total": 40, "completed": 38, "repeated": 1, "moved": 2}, "03": {"total": 34, "completed": 33, "moved": 2}, "04": {"total": 23, "completed": 23}, "05": {"total": 42, "completed": 42, "moved": 2}, "06": {"total": 32, "completed": 31, "moved": 3}, "07": {"total": 49, "completed": 44, "repeated": 3, "moved": 6}, "08": {"total": 36, "completed": 32, "repeated": 2, "moved": 7}, "1B": {"total": 74, "completed": 72, "repeated": 2, "moved": 5}, "2B": {"total": 83}}