{"01": {"total": 64, "completed": 60, "repeated": 1, "moved": 4}, "02": {"total": 67, "completed": 66, "moved": 5}, "03": {"total": 63, "completed": 59, "moved": 4}, "04": {"total": 80, "completed": 77, "moved": 11}, "05": {"total": 78, "completed": 69, "moved": 6}, "06": {"total": 71, "completed": 63, "moved": 4}, "07": {"total": 84, "completed": 74, "repeated": 2, "moved": 7}, "08": {"total": 82, "completed": 79, "moved": 11}, "1B": {"total": 236, "completed": 212, "repeated": 13, "moved": 29}, "2B": {"total": 205, "completed": 90, "repeated": 5, "moved": 5}, "3B": {"total": 112, "completed": 1, "repeated": 1, "moved": 2}}