{"01":{"total":81,"completed":61,"repeated":9,"moved":8},"02":{"total":95,"completed":75,"repeated":10,"moved":12},"03":{"total":75,"completed":55,"repeated":13,"moved":5},"04":{"total":72,"completed":54,"repeated":7,"moved":7},"05":{"total":70,"completed":57,"repeated":6,"moved":2},"06":{"total":79,"completed":59,"repeated":10,"moved":2},"07":{"total":66,"completed":55,"repeated":6},"08":{"total":59,"completed":46,"repeated":6,"moved":2},"1B":{"total":245,"completed":172,"repeated":55,"moved":33},"2B":{"total":184,"completed":68,"repeated":13,"moved":7},"3B":{"total":72,"repeated":1}}