{"01":{"total":69,"completed":65,"repeated":1,"moved":12},"02":{"total":40,"completed":34,"repeated":1,"moved":9},"03":{"total":46,"completed":38,"repeated":1,"moved":12},"04":{"total":55,"completed":45,"repeated":1,"moved":9},"05":{"total":51,"completed":44,"repeated":2,"moved":8},"06":{"total":47,"completed":42,"repeated":2,"moved":10},"07":{"total":44,"completed":41,"repeated":1,"moved":10},"08":{"total":55,"completed":49,"repeated":1,"moved":10},"1B":{"total":60,"completed":45,"repeated":6,"moved":10},"2B":{"total":71,"completed":12},"3B":{"total":19}}