{"01":{"total":75,"completed":67,"repeated":1,"moved":14},"02":{"total":66,"completed":60,"moved":9},"03":{"total":71,"completed":64,"repeated":1,"moved":9},"04":{"total":73,"completed":66,"repeated":1,"moved":10},"05":{"total":76,"completed":69,"moved":11},"06":{"total":51,"completed":49,"moved":6},"07":{"total":74,"completed":67,"repeated":2,"moved":7},"08":{"total":95,"completed":78,"repeated":2,"moved":13},"1B":{"total":149,"completed":135,"repeated":3,"moved":12},"2B":{"total":141,"completed":31,"repeated":3,"moved":4},"3B":{"total":20}}